Metadata-Version: 2.4
Name: iflow-mcp_wunrry_gen-http-sql-mcp
Version: 0.1.0
Summary: A universal SQL MCP server supporting multiple database engines
Requires-Python: >=3.11
License-File: LICENSE
Requires-Dist: fastmcp>=2.11.3
Requires-Dist: mysql-connector-python>=9.4.0
Requires-Dist: psycopg2-binary>=2.9.0
Requires-Dist: pyodbc>=5.0.0
Requires-Dist: sqlalchemy>=2.0.0
Requires-Dist: python-dotenv>=1.0.0
Dynamic: license-file
